deltaresult/__init__.py
deltaresult/__main__.py
deltaresult/deltaresult.py
deltaresult/main.py
deltaresult-0.0.1.dist-info/LICENSE
deltaresult-0.0.1.dist-info/METADATA
deltaresult-0.0.1.dist-info/WHEEL
deltaresult-0.0.1.dist-info/entry_points.txt
deltaresult-0.0.1.dist-info/top_level.txt
deltaresult-0.0.1.dist-info/RECORD
