Metadata-Version: 2.1
Name: deltaresult
Version: 0.0.1
Summary: Tracks changes for multiple script runs with similar results
Author: Andrea Micheloni
Author-email: author@example.com
License: UNKNOWN
Platform: UNKNOWN
Classifier: Programming Language :: Python :: 3
Classifier: License :: OSI Approved :: GNU Affero General Public License v3 or later (AGPLv3+)
Classifier: Operating System :: OS Independent
Requires-Python: >=3.6
License-File: LICENSE
Requires-Dist: GitPython (==3.1.26)
